dumda/__init__.py
dumda/baby-names.csv
dumda/cities.py
dumda/emails.py
dumda/last-names.txt
dumda/latin.xls
dumda/names.py
dumda/phones.py
dumda/text.py
dumda/world_cities.csv
dumda-2.3.dist-info/LICENCE
dumda-2.3.dist-info/METADATA
dumda-2.3.dist-info/WHEEL
dumda-2.3.dist-info/top_level.txt
dumda-2.3.dist-info/RECORD
