Metadata-Version: 2.1
Name: dumda
Version: 2.3
Summary: generate highly customizable dummy data for data science testing
Home-page: https://github.com/oliverbdot/dumda
Author: Oliver B.
Author-email: oliverbcontact@gmail.com
License: MIT
Keywords: data science,python
Platform: UNKNOWN
